hargassner/__init__.py
hargassner/client.py
hargassner-1.0.5.dist-info/licenses/LICENSE
hargassner-1.0.5.dist-info/METADATA
hargassner-1.0.5.dist-info/WHEEL
hargassner-1.0.5.dist-info/top_level.txt
hargassner-1.0.5.dist-info/RECORD
