Metadata-Version: 2.4
Name: hargassner
Version: 1.0.5
Summary: Query Hargassner equipment information through their Web API
Author-email: Markus Cserna <oss@cserna.at>
License: MIT License
Project-URL: Homepage, https://github.com/deawin/hargassner-api
Project-URL: Issues, https://github.com/deawin/hargassner-api/issues
Keywords: hargassner
Classifier: Programming Language :: Python :: 3
Classifier: License :: OSI Approved :: MIT License
Classifier: Operating System :: OS Independent
Requires-Python: >=3.8
License-File: LICENSE
Requires-Dist: requests~=2.31.0
Dynamic: license-file
